pptx2png/__init__.py
pptx2png/pptx2png.py
pptx2png-2025.1.dist-info/METADATA
pptx2png-2025.1.dist-info/WHEEL
pptx2png-2025.1.dist-info/top_level.txt
pptx2png-2025.1.dist-info/RECORD
