Metadata-Version: 2.4
Name: pptx2png
Version: 2025.1
Summary: A one-click Python library for converting .pptx files into .png images.
Home-page: https://github.com/Water-Run/pptx2png
Author: WaterRun
Author-email: 2263633954@qq.com
Classifier: Programming Language :: Python :: 3
Classifier: License :: OSI Approved :: MIT License
Classifier: Operating System :: Microsoft :: Windows
Classifier: Topic :: Multimedia :: Graphics :: Presentation
Requires-Python: >=3.5
Requires-Dist: pywin32
Dynamic: author
Dynamic: author-email
Dynamic: classifier
Dynamic: description
Dynamic: description-content-type
Dynamic: home-page
Dynamic: requires-dist
Dynamic: requires-python
Dynamic: summary
